pyqywe_miniapp/__init__.py
pyqywe_miniapp/miniapp.py
pyqywe_miniapp-1.0.0.dist-info/METADATA
pyqywe_miniapp-1.0.0.dist-info/WHEEL
pyqywe_miniapp-1.0.0.dist-info/top_level.txt
pyqywe_miniapp-1.0.0.dist-info/RECORD
